{
    "pooler": {
        "0": [
            [
                0.9918888888888888,
                0.9164999999999999
            ],
            [
                0.9897222222222222,
                0.916
            ],
            [
                0.9856111111111112,
                0.9179999999999999
            ],
            [
                0.9885555555555555,
                0.9215
            ]
        ]
    },
    "cls": {
        "0": [
            [
                0.5,
                0.5
            ],
            [
                0.5,
                0.5
            ],
            [
                0.5,
                0.5
            ],
            [
                0.5,
                0.5
            ]
        ],
        "1": [
            [
                0.9926666666666668,
                0.9604999999999999
            ],
            [
                0.9951111111111111,
                0.954
            ],
            [
                0.9935555555555556,
                0.9465
            ],
            [
                0.9948333333333332,
                0.9574999999999999
            ]
        ],
        "2": [
            [
                0.9884999999999998,
                0.9395
            ],
            [
                0.9943888888888888,
                0.9574999999999999
            ],
            [
                0.9931666666666666,
                0.9434999999999999
            ],
            [
                0.9895555555555557,
                0.9465
            ]
        ],
        "3": [
            [
                0.9918333333333333,
                0.9405000000000001
            ],
            [
                0.9939444444444444,
                0.9469999999999998
            ],
            [
                0.9919999999999998,
                0.938
            ],
            [
                0.9915555555555555,
                0.943
            ]
        ],
        "4": [
            [
                0.9938333333333332,
                0.9615
            ],
            [
                0.9965555555555554,
                0.9555
            ],
            [
                0.9920555555555554,
                0.953
            ],
            [
                0.9952222222222222,
                0.9545000000000001
            ]
        ],
        "5": [
            [
                0.9961111111111111,
                0.968
            ],
            [
                0.9971666666666665,
                0.9700000000000001
            ],
            [
                0.9949999999999999,
                0.9640000000000001
            ],
            [
                0.9945555555555554,
                0.9654999999999999
            ]
        ],
        "6": [
            [
                0.9939444444444444,
                0.968
            ],
            [
                0.998,
                0.9720000000000001
            ],
            [
                0.9951111111111111,
                0.9709999999999999
            ],
            [
                0.9949444444444444,
                0.9700000000000001
            ]
        ],
        "7": [
            [
                0.9967777777777778,
                0.9734999999999999
            ],
            [
                0.9968888888888887,
                0.97
            ],
            [
                0.9969444444444443,
                0.9730000000000001
            ],
            [
                0.9967222222222223,
                0.9755
            ]
        ],
        "8": [
            [
                0.9946666666666666,
                0.9720000000000001
            ],
            [
                0.9966666666666667,
                0.9719999999999999
            ],
            [
                0.9977222222222222,
                0.9774999999999998
            ],
            [
                0.9958333333333332,
                0.977
            ]
        ],
        "9": [
            [
                0.9888333333333333,
                0.9585000000000001
            ],
            [
                0.9947222222222221,
                0.9574999999999999
            ],
            [
                0.9949444444444444,
                0.9644999999999999
            ],
            [
                0.9951111111111111,
                0.96
            ]
        ],
        "10": [
            [
                0.9971666666666665,
                0.975
            ],
            [
                0.9979999999999999,
                0.974
            ],
            [
                0.9968888888888887,
                0.9720000000000001
            ],
            [
                0.9968888888888887,
                0.9654999999999999
            ]
        ],
        "11": [
            [
                0.9935555555555556,
                0.954
            ],
            [
                0.9921111111111113,
                0.951
            ],
            [
                0.9942777777777778,
                0.9545000000000001
            ],
            [
                0.9953333333333332,
                0.9605000000000002
            ]
        ],
        "12": [
            [
                0.9895000000000002,
                0.923
            ],
            [
                0.9910555555555556,
                0.9339999999999999
            ],
            [
                0.9892222222222221,
                0.9305
            ],
            [
                0.9900555555555556,
                0.931
            ]
        ]
    },
    "mean": {
        "0": [
            [
                0.9995,
                0.9949999999999999
            ],
            [
                0.9998333333333334,
                0.9905000000000002
            ],
            [
                0.9998888888888888,
                0.9945
            ],
            [
                0.9991666666666668,
                0.9960000000000001
            ]
        ],
        "1": [
            [
                0.9989444444444444,
                0.9890000000000001
            ],
            [
                0.9994999999999999,
                0.9904999999999999
            ],
            [
                0.9993333333333334,
                0.9919999999999998
            ],
            [
                0.9992222222222222,
                0.9934999999999998
            ]
        ],
        "2": [
            [
                0.9991666666666668,
                0.9934999999999998
            ],
            [
                0.9996666666666666,
                0.9925
            ],
            [
                0.9985555555555555,
                0.9904999999999999
            ],
            [
                0.999388888888889,
                0.9950000000000001
            ]
        ],
        "3": [
            [
                0.998388888888889,
                0.9899999999999999
            ],
            [
                0.9994444444444446,
                0.9914999999999999
            ],
            [
                0.9986111111111111,
                0.9889999999999999
            ],
            [
                0.9984444444444444,
                0.9925
            ]
        ],
        "4": [
            [
                0.998388888888889,
                0.9865
            ],
            [
                0.9989444444444444,
                0.9880000000000001
            ],
            [
                0.9984999999999999,
                0.9870000000000001
            ],
            [
                0.9987777777777778,
                0.9894999999999999
            ]
        ],
        "5": [
            [
                0.9984444444444444,
                0.9845
            ],
            [
                0.9988888888888889,
                0.984
            ],
            [
                0.9976111111111111,
                0.9894999999999998
            ],
            [
                0.9972222222222221,
                0.983
            ]
        ],
        "6": [
            [
                0.9970555555555556,
                0.982
            ],
            [
                0.9983888888888888,
                0.983
            ],
            [
                0.9965555555555554,
                0.9824999999999999
            ],
            [
                0.9970555555555556,
                0.984
            ]
        ],
        "7": [
            [
                0.9978888888888889,
                0.9804999999999999
            ],
            [
                0.9987222222222222,
                0.9824999999999999
            ],
            [
                0.9981666666666668,
                0.9855
            ],
            [
                0.9981666666666665,
                0.985
            ]
        ],
        "8": [
            [
                0.9977777777777778,
                0.9815000000000002
            ],
            [
                0.9983333333333333,
                0.9810000000000001
            ],
            [
                0.999,
                0.9834999999999999
            ],
            [
                0.9976111111111111,
                0.9819999999999999
            ]
        ],
        "9": [
            [
                0.9972777777777779,
                0.977
            ],
            [
                0.9972777777777777,
                0.9724999999999999
            ],
            [
                0.9978888888888887,
                0.9795
            ],
            [
                0.9969999999999999,
                0.9824999999999999
            ]
        ],
        "10": [
            [
                0.9976666666666667,
                0.9800000000000001
            ],
            [
                0.9974444444444444,
                0.9804999999999999
            ],
            [
                0.9986666666666666,
                0.9815000000000002
            ],
            [
                0.9976111111111111,
                0.9820000000000002
            ]
        ],
        "11": [
            [
                0.9962777777777777,
                0.9695
            ],
            [
                0.9979444444444443,
                0.9715
            ],
            [
                0.9947777777777776,
                0.9605
            ],
            [
                0.9939444444444444,
                0.9635
            ]
        ],
        "12": [
            [
                0.9948333333333332,
                0.945
            ],
            [
                0.9942222222222222,
                0.9404999999999999
            ],
            [
                0.9908333333333333,
                0.942
            ],
            [
                0.992888888888889,
                0.943
            ]
        ]
    },
    "haddamard": {
        "0": [
            [
                0.7769999999999999,
                0.5885
            ],
            [
                0.8062222222222223,
                0.587
            ],
            [
                0.8123333333333334,
                0.5940000000000001
            ],
            [
                0.7635,
                0.5715000000000001
            ]
        ],
        "1": [
            [
                0.8255000000000001,
                0.5670000000000001
            ],
            [
                0.8352222222222222,
                0.565
            ],
            [
                0.8568333333333333,
                0.5695
            ],
            [
                0.7625555555555555,
                0.552
            ]
        ],
        "2": [
            [
                0.8941666666666667,
                0.627
            ],
            [
                0.8917222222222222,
                0.6275
            ],
            [
                0.8450000000000001,
                0.6114999999999999
            ],
            [
                0.8198333333333334,
                0.6004999999999999
            ]
        ],
        "3": [
            [
                0.8817222222222222,
                0.639
            ],
            [
                0.820111111111111,
                0.6075
            ],
            [
                0.8473888888888889,
                0.637
            ],
            [
                0.8617777777777779,
                0.64
            ]
        ],
        "4": [
            [
                0.9032777777777777,
                0.6575
            ],
            [
                0.7917777777777777,
                0.6235
            ],
            [
                0.9027222222222221,
                0.667
            ],
            [
                0.8613333333333333,
                0.6575
            ]
        ],
        "5": [
            [
                0.8823333333333334,
                0.679
            ],
            [
                0.9301666666666668,
                0.677
            ],
            [
                0.9167222222222222,
                0.6900000000000001
            ],
            [
                0.9011111111111111,
                0.6725
            ]
        ],
        "6": [
            [
                0.9270555555555555,
                0.648
            ],
            [
                0.9275,
                0.6695
            ],
            [
                0.9375555555555556,
                0.6755
            ],
            [
                0.7937777777777778,
                0.6345
            ]
        ],
        "7": [
            [
                0.8840555555555556,
                0.6380000000000001
            ],
            [
                0.8323888888888888,
                0.6275
            ],
            [
                0.8962222222222224,
                0.646
            ],
            [
                0.925,
                0.648
            ]
        ],
        "8": [
            [
                0.9406111111111113,
                0.6599999999999999
            ],
            [
                0.9289444444444446,
                0.6604999999999999
            ],
            [
                0.9015000000000001,
                0.663
            ],
            [
                0.9412777777777779,
                0.657
            ]
        ],
        "9": [
            [
                0.8926666666666666,
                0.6315
            ],
            [
                0.929388888888889,
                0.6365000000000001
            ],
            [
                0.9195555555555555,
                0.6395000000000001
            ],
            [
                0.9137222222222222,
                0.643
            ]
        ],
        "10": [
            [
                0.9067222222222224,
                0.6869999999999999
            ],
            [
                0.9195,
                0.6900000000000001
            ],
            [
                0.9214444444444444,
                0.6869999999999999
            ],
            [
                0.9228333333333334,
                0.6849999999999999
            ]
        ],
        "11": [
            [
                0.9571111111111111,
                0.701
            ],
            [
                0.954111111111111,
                0.71
            ],
            [
                0.9179444444444445,
                0.7025000000000001
            ],
            [
                0.9478333333333332,
                0.712
            ]
        ],
        "12": [
            [
                0.931,
                0.6645000000000001
            ],
            [
                0.9146666666666666,
                0.665
            ],
            [
                0.9133333333333333,
                0.659
            ],
            [
                0.9091111111111113,
                0.668
            ]
        ]
    },
    "sum": {
        "0": [
            [
                0.9995,
                0.9945
            ],
            [
                0.9998888888888888,
                0.99
            ],
            [
                0.9999444444444444,
                0.9964999999999999
            ],
            [
                0.9992222222222222,
                0.9960000000000001
            ]
        ],
        "1": [
            [
                0.9988888888888889,
                0.9909999999999999
            ],
            [
                0.9995555555555555,
                0.9914999999999999
            ],
            [
                0.9991111111111112,
                0.991
            ],
            [
                0.9984999999999999,
                0.9929999999999998
            ]
        ],
        "2": [
            [
                0.9996111111111112,
                0.994
            ],
            [
                0.9992777777777778,
                0.9884999999999999
            ],
            [
                0.9986111111111111,
                0.9915
            ],
            [
                0.9988888888888889,
                0.9909999999999999
            ]
        ],
        "3": [
            [
                0.9984999999999999,
                0.9884999999999999
            ],
            [
                0.9990555555555556,
                0.9899999999999999
            ],
            [
                0.9981666666666665,
                0.9845
            ],
            [
                0.9984444444444444,
                0.992
            ]
        ],
        "4": [
            [
                0.9983333333333334,
                0.9870000000000001
            ],
            [
                0.9987222222222222,
                0.9865
            ],
            [
                0.9988333333333334,
                0.9884999999999999
            ],
            [
                0.9986111111111111,
                0.99
            ]
        ],
        "5": [
            [
                0.9982777777777778,
                0.9880000000000001
            ],
            [
                0.9988333333333334,
                0.9875
            ],
            [
                0.9984444444444444,
                0.991
            ],
            [
                0.9974999999999999,
                0.985
            ]
        ],
        "6": [
            [
                0.9974444444444444,
                0.9854999999999998
            ],
            [
                0.9983333333333333,
                0.9835
            ],
            [
                0.9974444444444444,
                0.9844999999999999
            ],
            [
                0.9974444444444444,
                0.985
            ]
        ],
        "7": [
            [
                0.9981111111111112,
                0.9819999999999999
            ],
            [
                0.9987222222222222,
                0.9809999999999999
            ],
            [
                0.9981666666666668,
                0.984
            ],
            [
                0.9982777777777777,
                0.986
            ]
        ],
        "8": [
            [
                0.9971666666666665,
                0.9799999999999999
            ],
            [
                0.9981666666666665,
                0.9819999999999999
            ],
            [
                0.9988888888888889,
                0.984
            ],
            [
                0.9973888888888889,
                0.9810000000000001
            ]
        ],
        "9": [
            [
                0.9973333333333333,
                0.978
            ],
            [
                0.9976666666666667,
                0.9724999999999999
            ],
            [
                0.9987222222222222,
                0.9824999999999999
            ],
            [
                0.9969999999999999,
                0.9829999999999999
            ]
        ],
        "10": [
            [
                0.9978333333333333,
                0.9795
            ],
            [
                0.9982777777777777,
                0.984
            ],
            [
                0.9989444444444444,
                0.9799999999999999
            ],
            [
                0.9969999999999999,
                0.9785
            ]
        ],
        "11": [
            [
                0.9963333333333333,
                0.9694999999999998
            ],
            [
                0.9976111111111109,
                0.9724999999999999
            ],
            [
                0.9954999999999998,
                0.9629999999999999
            ],
            [
                0.9929444444444446,
                0.959
            ]
        ],
        "12": [
            [
                0.9952222222222222,
                0.9444999999999999
            ],
            [
                0.9941666666666666,
                0.9404999999999999
            ],
            [
                0.9916666666666668,
                0.943
            ],
            [
                0.9931666666666666,
                0.946
            ]
        ]
    }
}